verdic_guard.py
verdic_guard-1.0.0.dist-info/METADATA
verdic_guard-1.0.0.dist-info/WHEEL
verdic_guard-1.0.0.dist-info/top_level.txt
verdic_guard-1.0.0.dist-info/RECORD
