Metadata-Version: 2.4
Name: verdic-guard
Version: 1.0.0
Summary: Python SDK for Verdic Guard execution validation
Home-page: https://github.com/verdic/verdic-guard-python
Author: Verdic
Author-email: support@verdic.dev
Project-URL: Bug Reports, https://github.com/verdic/verdic-guard-python/issues
Project-URL: Source, https://github.com/verdic/verdic-guard-python
Project-URL: Documentation, https://github.com/verdic/verdic-guard-python#readme
Classifier: Development Status :: 4 - Beta
Classifier: Intended Audience :: Developers
Classifier: License :: OSI Approved :: MIT License
Classifier: Operating System :: OS Independent
Classifier: Programming Language :: Python :: 3
Classifier: Programming Language :: Python :: 3.7
Classifier: Programming Language :: Python :: 3.8
Classifier: Programming Language :: Python :: 3.9
Classifier: Programming Language :: Python :: 3.10
Classifier: Programming Language :: Python :: 3.11
Classifier: Programming Language :: Python :: 3.12
Requires-Python: >=3.7
Requires-Dist: requests>=2.25.0
Dynamic: author
Dynamic: author-email
Dynamic: classifier
Dynamic: description
Dynamic: description-content-type
Dynamic: home-page
Dynamic: project-url
Dynamic: requires-dist
Dynamic: requires-python
Dynamic: summary
